csv_etl/__init__.py
csv_etl/cli.py
csv_etl/csv_etl.py
csv_etl/rules.py
csv_etl-0.1.3.dist-info/METADATA
csv_etl-0.1.3.dist-info/WHEEL
csv_etl-0.1.3.dist-info/entry_points.txt
csv_etl-0.1.3.dist-info/top_level.txt
csv_etl-0.1.3.dist-info/RECORD
