Metadata-Version: 2.1
Name: csv-etl
Version: 0.1.3
Summary: A rules based approach to performing ETL operations on csv files.
Home-page: https://github.com/winslowdibona/csv-etl
Author: Winslow DiBona
License: MIT
Platform: UNKNOWN
Requires-Dist: pyyaml
Requires-Dist: Click
